pepystats/__init__.py
pepystats/api.py
pepystats/cli.py
pepystats-0.2.2.dist-info/licenses/LICENSE
pepystats-0.2.2.dist-info/METADATA
pepystats-0.2.2.dist-info/WHEEL
pepystats-0.2.2.dist-info/entry_points.txt
pepystats-0.2.2.dist-info/top_level.txt
pepystats-0.2.2.dist-info/RECORD
