Metadata-Version: 2.4
Name: pepystats
Version: 0.2.2
Summary: Lightweight Python client & CLI for pepy.tech download stats
Author: Ian Ellis
Author-email: ellisiana@gmail.com
License:                     GNU GENERAL PUBLIC LICENSE
Project-URL: Homepage, https://github.com/magicalbob/pepystats/wiki
Project-URL: Repository, https://github.com/magicalbob/pepystats
Project-URL: Issues, https://github.com/magicalbob/pepystats/issues
Project-URL: Changelog, https://github.com/magicalbob/pepystats/releases
Classifier: Development Status :: 3 - Alpha
Classifier: Environment :: Console
Classifier: Intended Audience :: Developers
Classifier: Programming Language :: Python :: 3
Classifier: Programming Language :: Python :: 3.9
Classifier: Programming Language :: Python :: 3.10
Classifier: Programming Language :: Python :: 3.11
Classifier: Programming Language :: Python :: 3.12
Classifier: Operating System :: OS Independent
Classifier: Topic :: Software Development :: Build Tools
Classifier: Topic :: Utilities
Requires-Python: >=3.8
License-File: LICENSE
Requires-Dist: requests>=2.31.0
Requires-Dist: pandas>=2.0.0
Requires-Dist: matplotlib>=3.7.0
Requires-Dist: tabulate>=0.9.0
Provides-Extra: dev
Requires-Dist: pytest>=8.2; extra == "dev"
Requires-Dist: pytest-cov>=6.0; extra == "dev"
Requires-Dist: build>=1.2; extra == "dev"
Requires-Dist: twine>=5.0; extra == "dev"
Dynamic: license-file
